bui/__init__.py
bui/cmd_parser.py
bui/geometry.py
bui/keyboard.py
bui/log.py
bui/tasks.py
bui/tools.py
bui/control/__init__.py
bui/control/base.py
bui/control/change.py
bui/control/check.py
bui/control/click.py
bui/control/close.py
bui/control/exceptions.py
bui/control/init.py
bui/control/log.py
bui/control/press.py
bui/control/release.py
bui/control/right_click.py
bui/control/select.py
bui/control/type.py
bui/layout/__init__.py
bui/layout/attr.py
bui/layout/button.py
bui/layout/checkbox.py
bui/layout/choice.py
bui/layout/col.py
bui/layout/component.py
bui/layout/context.py
bui/layout/dialog.py
bui/layout/item.py
bui/layout/layout.py
bui/layout/list.py
bui/layout/menu.py
bui/layout/menubar.py
bui/layout/parser.py
bui/layout/radio.py
bui/layout/table.py
bui/layout/text.py
bui/layout/window.py
bui/specific/__init__.py
bui/specific/base/__init__.py
bui/specific/base/base.py
bui/specific/base/button.py
bui/specific/base/checkbox.py
bui/specific/base/context.py
bui/specific/base/dialog.py
bui/specific/base/item.py
bui/specific/base/list.py
bui/specific/base/menu.py
bui/specific/base/menubar.py
bui/specific/base/radio.py
bui/specific/base/table.py
bui/specific/base/text.py
bui/specific/base/window.py
bui/specific/wx4/__init__.py
bui/specific/wx4/app.py
bui/specific/wx4/button.py
bui/specific/wx4/checkbox.py
bui/specific/wx4/constants.py
bui/specific/wx4/context.py
bui/specific/wx4/dialog.py
bui/specific/wx4/interactive.py
bui/specific/wx4/item.py
bui/specific/wx4/list.py
bui/specific/wx4/log.py
bui/specific/wx4/menu.py
bui/specific/wx4/menubar.py
bui/specific/wx4/radio.py
bui/specific/wx4/shared.py
bui/specific/wx4/table.py
bui/specific/wx4/text.py
bui/specific/wx4/thread.py
bui/specific/wx4/window.py
bui/widget/__init__.py
bui/widget/base.py
bui/widget/button.py
bui/widget/checkbox.py
bui/widget/context.py
bui/widget/dialog.py
bui/widget/item.py
bui/widget/list.py
bui/widget/menu.py
bui/widget/menubar.py
bui/widget/radio.py
bui/widget/table.py
bui/widget/text.py
bui-0.3.3.dist-info/LICENSE
bui-0.3.3.dist-info/METADATA
bui-0.3.3.dist-info/WHEEL
bui-0.3.3.dist-info/top_level.txt
bui-0.3.3.dist-info/RECORD
