Metadata-Version: 2.1
Name: bui
Version: 0.3.3
Summary: The Blind User Interface: the interface you can design with your eyes closed.
Home-page: https://github.com/vincent-lg/bui/
Author: Vincent Le Goff
Author-email: vincent.legoff.srs@gmail.com
Classifier: Development Status :: 1 - Planning
Classifier: Intended Audience :: Developers
Classifier: License :: OSI Approved :: BSD License
Classifier: Operating System :: OS Independent
Classifier: Programming Language :: Python :: 3.6
Classifier: Programming Language :: Python :: 3.7
Requires-Python: >=3.6
License-File: LICENSE
Requires-Dist: Logbook (==1.5.2)
Requires-Dist: wxPython (==4.2.0) ; platform_system == "Windows"
Requires-Dist: Pypubsub (==4.0.3) ; platform_system == "Windows"
Provides-Extra: demo
Requires-Dist: aiodns (==2.0.0) ; extra == 'demo'
Requires-Dist: aiofiles (==0.4.0) ; extra == 'demo'
Requires-Dist: aiohttp (==3.5.4) ; extra == 'demo'
Requires-Dist: cchardet (==2.1.4) ; extra == 'demo'
